[
  {
    "title": "Rio Sul Valley na Flumisul",
    "date": {
      "day": "2",
      "month": "Agosto",
      "year": 2018
    },
    "innerLink": "inner.html",
    "link": "https://www.facebook.com/events/296497684254807/",
    "price": "Gratuito",
    "location": {
      "city": "Volta Redodna",
      "state": "RJ",
      "address": "Parque da Cidade - Barra Mansa",
      "locationUrl": "https://www.google.com.br/maps/place/Parque+da+Cidade/@-22.5366949,-44.1821107,15z/data=!4m2!3m1!1s0x0:0x2503509c4dc3e083?sa=X&ved=2ahUKEwjUuvONr7_cAhUDlJAKHRQeDQIQ_BIwE3oECAoQCw"
    },
    "image": "https://scontent.fcfc1-1.fna.fbcdn.net/v/t1.0-9/37888966_2235514233132128_8516997513213902848_o.jpg?_nc_cat=0&oh=d7072985496c46994b27cda708122522&oe=5C0B2EE9",
    "shortDescription": "- Mentorias gratuitas com os melhores especialistas da região;-Quiz RSV pelo nosso app que já está no ar, concorrendo a prêmios;- Rodas de conversa e palestras sobre diversos temas relacionados ao empreendedorismo, inovação e tecnologia."
  }
]
